[
  {
    "provider_id": "p1",
    "name": "City Urgent Care - Midtown",
    "provider_type": "urgent_care",
    "distance_km": 1.8,
    "next_available_slot": "2026-04-13T15:30:00-04:00",
    "address": "123 Midtown Ave, New York, NY"
  },
  {
    "provider_id": "p2",
    "name": "Metro General Hospital",
    "provider_type": "hospital",
    "distance_km": 4.5,
    "next_available_slot": "2026-04-13T17:00:00-04:00",
    "address": "88 Grand St, New York, NY"
  },
  {
    "provider_id": "p3",
    "name": "Eastside Family Clinic",
    "provider_type": "clinic",
    "distance_km": 3.2,
    "next_available_slot": "2026-04-13T16:00:00-04:00",
    "address": "42 East Clinic Rd, New York, NY"
  }
]
